comet_cli-0.1.3.dist-info/DESCRIPTION.rst
comet_cli-0.1.3.dist-info/METADATA
comet_cli-0.1.3.dist-info/RECORD
comet_cli-0.1.3.dist-info/WHEEL
comet_cli-0.1.3.dist-info/entry_points.txt
comet_cli-0.1.3.dist-info/metadata.json
comet_cli-0.1.3.dist-info/top_level.txt
cometcli/__init__.py
cometcli/cli.py
cometcli/datasets.py
cometcli/query.py
cometcli/utils.py
