Metadata-Version: 2.0
Name: comet-cli
Version: 0.1.3
Summary: CLI for comet, a privacy preserving data management tool
Home-page: UNKNOWN
Author: Tabish Imran
Author-email: vector@s20.ai
License: BSD
Platform: any
Classifier: Development Status :: 4 - Beta
Classifier: Environment :: Console
Classifier: Intended Audience :: Developers
Classifier: License :: OSI Approved :: BSD License
Classifier: Operating System :: POSIX
Classifier: Operating System :: MacOS
Classifier: Operating System :: Unix
Classifier: Operating System :: Microsoft :: Windows
Classifier: Programming Language :: Python
Classifier: Programming Language :: Python :: 2
Classifier: Programming Language :: Python :: 3
Classifier: Topic :: Software Development :: Libraries :: Python Modules
Requires-Python: >=3
Requires-Dist: click
Requires-Dist: PyYAML
Requires-Dist: requests
Requires-Dist: xxhash
